setup.py
collect_exceptions/__init__.py
collect_exceptions.egg-info/PKG-INFO
collect_exceptions.egg-info/SOURCES.txt
collect_exceptions.egg-info/dependency_links.txt
collect_exceptions.egg-info/not-zip-safe
collect_exceptions.egg-info/top_level.txt
collect_exceptions/contrib/__init__.py
collect_exceptions/contrib/celery/__init__.py
collect_exceptions/contrib/django/__init__.py
collect_exceptions/contrib/django/admin.py
collect_exceptions/contrib/django/models.py
collect_exceptions/contrib/django/tests.py
collect_exceptions/contrib/django/views.py