Metadata-Version: 1.0
Name: collect-exceptions
Version: 0.0.5
Summary: python exception collector
Home-page: https://github.com/Yemsheng/collect-exceptions
Author: Yemsheng
Author-email: msheng.ye@foxmail.com
License: UNKNOWN
Platform: UNKNOWN
